{
  "startTimeStamp": "2020-12-11T05:00:00Z",
  "endTimeStamp": "2020-12-11T11:00:00Z",
  "timeRange": [
    {
      "timeStamp": "2020-12-11T05:00:00Z",
      "items": [
        {
          "name": "botPercent",
          "value": "43.983620"
        },
        {
          "name": "humanPercent",
          "value": "56.016380"
        }
      ]
    },
    {
      "timeStamp": "2020-12-11T05:15:00Z",
      "items": [
        {
          "name": "botPercent",
          "value": "43.336354"
        },
        {
          "name": "humanPercent",
          "value": "56.663646"
        }
      ]
    },
    {
      "timeStamp": "2020-12-11T05:30:00Z",
      "items": [
        {
          "name": "botPercent",
          "value": "42.767361"
        },
        {
          "name": "humanPercent",
          "value": "57.232639"
        }
      ]
    },
    {
      "timeStamp": "2020-12-11T05:45:00Z",
      "items": [
        {
          "name": "botPercent",
          "value": "42.770754"
        },
        {
          "name": "humanPercent",
          "value": "57.229246"
        }
      ]
    },
    {
      "timeStamp": "2020-12-11T06:00:00Z",
      "items": [
        {
          "name": "botPercent",
          "value": "42.758899"
        },
        {
          "name": "humanPercent",
          "value": "57.241101"
        }
      ]
    },
    {
      "timeStamp": "2020-12-11T06:15:00Z",
      "items": [
        {
          "name": "botPercent",
          "value": "43.270235"
        },
        {
          "name": "humanPercent",
          "value": "56.729765"
        }
      ]
    },
    {
      "timeStamp": "2020-12-11T06:30:00Z",
      "items": [
        {
          "name": "botPercent",
          "value": "43.678175"
        },
        {
          "name": "humanPercent",
          "value": "56.321825"
        }
      ]
    },
    {
      "timeStamp": "2020-12-11T06:45:00Z",
      "items": [
        {
          "name": "botPercent",
          "value": "43.431608"
        },
        {
          "name": "humanPercent",
          "value": "56.568392"
        }
      ]
    },
    {
      "timeStamp": "2020-12-11T07:00:00Z",
      "items": [
        {
          "name": "botPercent",
          "value": "43.305797"
        },
        {
          "name": "humanPercent",
          "value": "56.694203"
        }
      ]
    },
    {
      "timeStamp": "2020-12-11T07:15:00Z",
      "items": [
        {
          "name": "botPercent",
          "value": "42.789078"
        },
        {
          "name": "humanPercent",
          "value": "57.210922"
        }
      ]
    },
    {
      "timeStamp": "2020-12-11T07:30:00Z",
      "items": [
        {
          "name": "botPercent",
          "value": "43.226371"
        },
        {
          "name": "humanPercent",
          "value": "56.773629"
        }
      ]
    },
    {
      "timeStamp": "2020-12-11T07:45:00Z",
      "items": [
        {
          "name": "botPercent",
          "value": "42.649142"
        },
        {
          "name": "humanPercent",
          "value": "57.350858"
        }
      ]
    },
    {
      "timeStamp": "2020-12-11T08:00:00Z",
      "items": [
        {
          "name": "botPercent",
          "value": "42.731795"
        },
        {
          "name": "humanPercent",
          "value": "57.268205"
        }
      ]
    },
    {
      "timeStamp": "2020-12-11T08:15:00Z",
      "items": [
        {
          "name": "botPercent",
          "value": "42.939160"
        },
        {
          "name": "humanPercent",
          "value": "57.060840"
        }
      ]
    },
    {
      "timeStamp": "2020-12-11T08:30:00Z",
      "items": [
        {
          "name": "botPercent",
          "value": "42.202585"
        },
        {
          "name": "humanPercent",
          "value": "57.797415"
        }
      ]
    },
    {
      "timeStamp": "2020-12-11T08:45:00Z",
      "items": [
        {
          "name": "botPercent",
          "value": "42.047973"
        },
        {
          "name": "humanPercent",
          "value": "57.952027"
        }
      ]
    },
    {
      "timeStamp": "2020-12-11T09:00:00Z",
      "items": [
        {
          "name": "botPercent",
          "value": "42.528094"
        },
        {
          "name": "humanPercent",
          "value": "57.471906"
        }
      ]
    },
    {
      "timeStamp": "2020-12-11T09:15:00Z",
      "items": [
        {
          "name": "botPercent",
          "value": "42.294206"
        },
        {
          "name": "humanPercent",
          "value": "57.705794"
        }
      ]
    },
    {
      "timeStamp": "2020-12-11T09:30:00Z",
      "items": [
        {
          "name": "botPercent",
          "value": "41.826065"
        },
        {
          "name": "humanPercent",
          "value": "58.173935"
        }
      ]
    },
    {
      "timeStamp": "2020-12-11T09:45:00Z",
      "items": [
        {
          "name": "botPercent",
          "value": "41.395097"
        },
        {
          "name": "humanPercent",
          "value": "58.604903"
        }
      ]
    },
    {
      "timeStamp": "2020-12-11T10:00:00Z",
      "items": [
        {
          "name": "botPercent",
          "value": "41.671389"
        },
        {
          "name": "humanPercent",
          "value": "58.328611"
        }
      ]
    },
    {
      "timeStamp": "2020-12-11T10:15:00Z",
      "items": [
        {
          "name": "botPercent",
          "value": "41.500518"
        },
        {
          "name": "humanPercent",
          "value": "58.499482"
        }
      ]
    },
    {
      "timeStamp": "2020-12-11T10:30:00Z",
      "items": [
        {
          "name": "botPercent",
          "value": "40.835854"
        },
        {
          "name": "humanPercent",
          "value": "59.164146"
        }
      ]
    },
    {
      "timeStamp": "2020-12-11T10:45:00Z",
      "items": [
        {
          "name": "botPercent",
          "value": "40.908645"
        },
        {
          "name": "humanPercent",
          "value": "59.091355"
        }
      ]
    },
    {
      "timeStamp": "2020-12-11T11:00:00Z",
      "items": [
        {
          "name": "botPercent",
          "value": "41.137754"
        },
        {
          "name": "humanPercent",
          "value": "58.862246"
        }
      ]
    }
  ]
}