{
  "startTimeStamp": "2020-10-15T11:00:00Z",
  "endTimeStamp": "2020-10-15T17:00:00Z",
  "timeRange": [
    {
      "timeStamp": "2020-10-15T11:00:00Z",
      "items": [
        {
          "name": "botPercent",
          "value": "40.892327"
        },
        {
          "name": "humanPercent",
          "value": "59.107673"
        }
      ]
    },
    {
      "timeStamp": "2020-10-15T11:15:00Z",
      "items": [
        {
          "name": "botPercent",
          "value": "40.699539"
        },
        {
          "name": "humanPercent",
          "value": "59.300461"
        }
      ]
    },
    {
      "timeStamp": "2020-10-15T11:30:00Z",
      "items": [
        {
          "name": "botPercent",
          "value": "40.961227"
        },
        {
          "name": "humanPercent",
          "value": "59.038773"
        }
      ]
    },
    {
      "timeStamp": "2020-10-15T11:45:00Z",
      "items": [
        {
          "name": "botPercent",
          "value": "40.459744"
        },
        {
          "name": "humanPercent",
          "value": "59.540256"
        }
      ]
    },
    {
      "timeStamp": "2020-10-15T12:00:00Z",
      "items": [
        {
          "name": "botPercent",
          "value": "40.423580"
        },
        {
          "name": "humanPercent",
          "value": "59.576420"
        }
      ]
    },
    {
      "timeStamp": "2020-10-15T12:15:00Z",
      "items": [
        {
          "name": "botPercent",
          "value": "40.291270"
        },
        {
          "name": "humanPercent",
          "value": "59.708730"
        }
      ]
    },
    {
      "timeStamp": "2020-10-15T12:30:00Z",
      "items": [
        {
          "name": "botPercent",
          "value": "40.028780"
        },
        {
          "name": "humanPercent",
          "value": "59.971220"
        }
      ]
    },
    {
      "timeStamp": "2020-10-15T12:45:00Z",
      "items": [
        {
          "name": "botPercent",
          "value": "39.084608"
        },
        {
          "name": "humanPercent",
          "value": "60.915392"
        }
      ]
    },
    {
      "timeStamp": "2020-10-15T13:00:00Z",
      "items": [
        {
          "name": "botPercent",
          "value": "39.232832"
        },
        {
          "name": "humanPercent",
          "value": "60.767168"
        }
      ]
    },
    {
      "timeStamp": "2020-10-15T13:15:00Z",
      "items": [
        {
          "name": "botPercent",
          "value": "38.596218"
        },
        {
          "name": "humanPercent",
          "value": "61.403782"
        }
      ]
    },
    {
      "timeStamp": "2020-10-15T13:30:00Z",
      "items": [
        {
          "name": "botPercent",
          "value": "38.721487"
        },
        {
          "name": "humanPercent",
          "value": "61.278513"
        }
      ]
    },
    {
      "timeStamp": "2020-10-15T13:45:00Z",
      "items": [
        {
          "name": "botPercent",
          "value": "38.863266"
        },
        {
          "name": "humanPercent",
          "value": "61.136734"
        }
      ]
    },
    {
      "timeStamp": "2020-10-15T14:00:00Z",
      "items": [
        {
          "name": "botPercent",
          "value": "38.852511"
        },
        {
          "name": "humanPercent",
          "value": "61.147489"
        }
      ]
    },
    {
      "timeStamp": "2020-10-15T14:15:00Z",
      "items": [
        {
          "name": "botPercent",
          "value": "38.001803"
        },
        {
          "name": "humanPercent",
          "value": "61.998197"
        }
      ]
    },
    {
      "timeStamp": "2020-10-15T14:30:00Z",
      "items": [
        {
          "name": "botPercent",
          "value": "38.223206"
        },
        {
          "name": "humanPercent",
          "value": "61.776794"
        }
      ]
    },
    {
      "timeStamp": "2020-10-15T14:45:00Z",
      "items": [
        {
          "name": "botPercent",
          "value": "37.891826"
        },
        {
          "name": "humanPercent",
          "value": "62.108174"
        }
      ]
    },
    {
      "timeStamp": "2020-10-15T15:00:00Z",
      "items": [
        {
          "name": "botPercent",
          "value": "37.823593"
        },
        {
          "name": "humanPercent",
          "value": "62.176407"
        }
      ]
    },
    {
      "timeStamp": "2020-10-15T15:15:00Z",
      "items": [
        {
          "name": "botPercent",
          "value": "37.401867"
        },
        {
          "name": "humanPercent",
          "value": "62.598133"
        }
      ]
    },
    {
      "timeStamp": "2020-10-15T15:30:00Z",
      "items": [
        {
          "name": "botPercent",
          "value": "37.219341"
        },
        {
          "name": "humanPercent",
          "value": "62.780659"
        }
      ]
    },
    {
      "timeStamp": "2020-10-15T15:45:00Z",
      "items": [
        {
          "name": "botPercent",
          "value": "37.073206"
        },
        {
          "name": "humanPercent",
          "value": "62.926794"
        }
      ]
    },
    {
      "timeStamp": "2020-10-15T16:00:00Z",
      "items": [
        {
          "name": "botPercent",
          "value": "37.294410"
        },
        {
          "name": "humanPercent",
          "value": "62.705590"
        }
      ]
    },
    {
      "timeStamp": "2020-10-15T16:15:00Z",
      "items": [
        {
          "name": "botPercent",
          "value": "36.833060"
        },
        {
          "name": "humanPercent",
          "value": "63.166940"
        }
      ]
    },
    {
      "timeStamp": "2020-10-15T16:30:00Z",
      "items": [
        {
          "name": "botPercent",
          "value": "37.059540"
        },
        {
          "name": "humanPercent",
          "value": "62.940460"
        }
      ]
    },
    {
      "timeStamp": "2020-10-15T16:45:00Z",
      "items": [
        {
          "name": "botPercent",
          "value": "36.625674"
        },
        {
          "name": "humanPercent",
          "value": "63.374326"
        }
      ]
    },
    {
      "timeStamp": "2020-10-15T17:00:00Z",
      "items": [
        {
          "name": "botPercent",
          "value": "36.814556"
        },
        {
          "name": "humanPercent",
          "value": "63.185444"
        }
      ]
    }
  ]
}