{
  "startTimeStamp": "2020-11-25T05:00:00Z",
  "endTimeStamp": "2020-11-25T11:00:00Z",
  "timeRange": [
    {
      "timeStamp": "2020-11-25T05:00:00Z",
      "items": [
        {
          "name": "botPercent",
          "value": "44.252304"
        },
        {
          "name": "humanPercent",
          "value": "55.747696"
        }
      ]
    },
    {
      "timeStamp": "2020-11-25T05:15:00Z",
      "items": [
        {
          "name": "botPercent",
          "value": "43.896754"
        },
        {
          "name": "humanPercent",
          "value": "56.103246"
        }
      ]
    },
    {
      "timeStamp": "2020-11-25T05:30:00Z",
      "items": [
        {
          "name": "botPercent",
          "value": "43.593346"
        },
        {
          "name": "humanPercent",
          "value": "56.406654"
        }
      ]
    },
    {
      "timeStamp": "2020-11-25T05:45:00Z",
      "items": [
        {
          "name": "botPercent",
          "value": "43.326063"
        },
        {
          "name": "humanPercent",
          "value": "56.673937"
        }
      ]
    },
    {
      "timeStamp": "2020-11-25T06:00:00Z",
      "items": [
        {
          "name": "botPercent",
          "value": "43.540248"
        },
        {
          "name": "humanPercent",
          "value": "56.459752"
        }
      ]
    },
    {
      "timeStamp": "2020-11-25T06:15:00Z",
      "items": [
        {
          "name": "botPercent",
          "value": "43.236028"
        },
        {
          "name": "humanPercent",
          "value": "56.763972"
        }
      ]
    },
    {
      "timeStamp": "2020-11-25T06:30:00Z",
      "items": [
        {
          "name": "botPercent",
          "value": "43.476387"
        },
        {
          "name": "humanPercent",
          "value": "56.523613"
        }
      ]
    },
    {
      "timeStamp": "2020-11-25T06:45:00Z",
      "items": [
        {
          "name": "botPercent",
          "value": "43.070495"
        },
        {
          "name": "humanPercent",
          "value": "56.929505"
        }
      ]
    },
    {
      "timeStamp": "2020-11-25T07:00:00Z",
      "items": [
        {
          "name": "botPercent",
          "value": "43.988891"
        },
        {
          "name": "humanPercent",
          "value": "56.011109"
        }
      ]
    },
    {
      "timeStamp": "2020-11-25T07:15:00Z",
      "items": [
        {
          "name": "botPercent",
          "value": "44.343948"
        },
        {
          "name": "humanPercent",
          "value": "55.656052"
        }
      ]
    },
    {
      "timeStamp": "2020-11-25T07:30:00Z",
      "items": [
        {
          "name": "botPercent",
          "value": "44.052052"
        },
        {
          "name": "humanPercent",
          "value": "55.947948"
        }
      ]
    },
    {
      "timeStamp": "2020-11-25T07:45:00Z",
      "items": [
        {
          "name": "botPercent",
          "value": "43.511609"
        },
        {
          "name": "humanPercent",
          "value": "56.488391"
        }
      ]
    },
    {
      "timeStamp": "2020-11-25T08:00:00Z",
      "items": [
        {
          "name": "botPercent",
          "value": "43.236653"
        },
        {
          "name": "humanPercent",
          "value": "56.763347"
        }
      ]
    },
    {
      "timeStamp": "2020-11-25T08:15:00Z",
      "items": [
        {
          "name": "botPercent",
          "value": "43.062822"
        },
        {
          "name": "humanPercent",
          "value": "56.937178"
        }
      ]
    },
    {
      "timeStamp": "2020-11-25T08:30:00Z",
      "items": [
        {
          "name": "botPercent",
          "value": "43.132440"
        },
        {
          "name": "humanPercent",
          "value": "56.867560"
        }
      ]
    },
    {
      "timeStamp": "2020-11-25T08:45:00Z",
      "items": [
        {
          "name": "botPercent",
          "value": "42.495428"
        },
        {
          "name": "humanPercent",
          "value": "57.504572"
        }
      ]
    },
    {
      "timeStamp": "2020-11-25T09:00:00Z",
      "items": [
        {
          "name": "botPercent",
          "value": "42.832104"
        },
        {
          "name": "humanPercent",
          "value": "57.167896"
        }
      ]
    },
    {
      "timeStamp": "2020-11-25T09:15:00Z",
      "items": [
        {
          "name": "botPercent",
          "value": "42.553481"
        },
        {
          "name": "humanPercent",
          "value": "57.446519"
        }
      ]
    },
    {
      "timeStamp": "2020-11-25T09:30:00Z",
      "items": [
        {
          "name": "botPercent",
          "value": "42.462072"
        },
        {
          "name": "humanPercent",
          "value": "57.537928"
        }
      ]
    },
    {
      "timeStamp": "2020-11-25T09:45:00Z",
      "items": [
        {
          "name": "botPercent",
          "value": "41.934331"
        },
        {
          "name": "humanPercent",
          "value": "58.065669"
        }
      ]
    },
    {
      "timeStamp": "2020-11-25T10:00:00Z",
      "items": [
        {
          "name": "botPercent",
          "value": "41.821801"
        },
        {
          "name": "humanPercent",
          "value": "58.178199"
        }
      ]
    },
    {
      "timeStamp": "2020-11-25T10:15:00Z",
      "items": [
        {
          "name": "botPercent",
          "value": "41.979848"
        },
        {
          "name": "humanPercent",
          "value": "58.020152"
        }
      ]
    },
    {
      "timeStamp": "2020-11-25T10:30:00Z",
      "items": [
        {
          "name": "botPercent",
          "value": "42.298106"
        },
        {
          "name": "humanPercent",
          "value": "57.701894"
        }
      ]
    },
    {
      "timeStamp": "2020-11-25T10:45:00Z",
      "items": [
        {
          "name": "botPercent",
          "value": "41.625459"
        },
        {
          "name": "humanPercent",
          "value": "58.374541"
        }
      ]
    },
    {
      "timeStamp": "2020-11-25T11:00:00Z",
      "items": [
        {
          "name": "botPercent",
          "value": "42.064754"
        },
        {
          "name": "humanPercent",
          "value": "57.935246"
        }
      ]
    }
  ]
}