{
  "startTimeStamp": "2020-12-07T05:00:00Z",
  "endTimeStamp": "2020-12-07T11:00:00Z",
  "timeRange": [
    {
      "timeStamp": "2020-12-07T05:00:00Z",
      "items": [
        {
          "name": "mobilePercent",
          "value": "53.051725"
        },
        {
          "name": "desktopPercent",
          "value": "46.952635"
        },
        {
          "name": "otherDevicePercent",
          "value": "0.134082"
        }
      ]
    },
    {
      "timeStamp": "2020-12-07T05:15:00Z",
      "items": [
        {
          "name": "mobilePercent",
          "value": "53.209199"
        },
        {
          "name": "desktopPercent",
          "value": "46.794052"
        },
        {
          "name": "otherDevicePercent",
          "value": "0.102963"
        }
      ]
    },
    {
      "timeStamp": "2020-12-07T05:30:00Z",
      "items": [
        {
          "name": "mobilePercent",
          "value": "53.308020"
        },
        {
          "name": "desktopPercent",
          "value": "46.700634"
        },
        {
          "name": "otherDevicePercent",
          "value": "0.089786"
        }
      ]
    },
    {
      "timeStamp": "2020-12-07T05:45:00Z",
      "items": [
        {
          "name": "mobilePercent",
          "value": "52.919611"
        },
        {
          "name": "desktopPercent",
          "value": "47.085702"
        },
        {
          "name": "otherDevicePercent",
          "value": "0.116891"
        }
      ]
    },
    {
      "timeStamp": "2020-12-07T06:00:00Z",
      "items": [
        {
          "name": "mobilePercent",
          "value": "52.805558"
        },
        {
          "name": "desktopPercent",
          "value": "47.200739"
        },
        {
          "name": "otherDevicePercent",
          "value": "0.089199"
        }
      ]
    },
    {
      "timeStamp": "2020-12-07T06:15:00Z",
      "items": [
        {
          "name": "mobilePercent",
          "value": "52.493658"
        },
        {
          "name": "desktopPercent",
          "value": "47.508431"
        },
        {
          "name": "otherDevicePercent",
          "value": "0.086654"
        }
      ]
    },
    {
      "timeStamp": "2020-12-07T06:30:00Z",
      "items": [
        {
          "name": "mobilePercent",
          "value": "51.533169"
        },
        {
          "name": "desktopPercent",
          "value": "48.469912"
        },
        {
          "name": "otherDevicePercent",
          "value": "0.093448"
        }
      ]
    },
    {
      "timeStamp": "2020-12-07T06:45:00Z",
      "items": [
        {
          "name": "mobilePercent",
          "value": "50.554724"
        },
        {
          "name": "desktopPercent",
          "value": "49.448333"
        },
        {
          "name": "otherDevicePercent",
          "value": "0.092709"
        }
      ]
    },
    {
      "timeStamp": "2020-12-07T07:00:00Z",
      "items": [
        {
          "name": "mobilePercent",
          "value": "50.781052"
        },
        {
          "name": "desktopPercent",
          "value": "49.220972"
        },
        {
          "name": "otherDevicePercent",
          "value": "0.077953"
        }
      ]
    },
    {
      "timeStamp": "2020-12-07T07:15:00Z",
      "items": [
        {
          "name": "mobilePercent",
          "value": "50.901930"
        },
        {
          "name": "desktopPercent",
          "value": "49.100110"
        },
        {
          "name": "otherDevicePercent",
          "value": "0.084684"
        }
      ]
    },
    {
      "timeStamp": "2020-12-07T07:30:00Z",
      "items": [
        {
          "name": "mobilePercent",
          "value": "50.244961"
        },
        {
          "name": "desktopPercent",
          "value": "49.762139"
        },
        {
          "name": "otherDevicePercent",
          "value": "0.105491"
        }
      ]
    },
    {
      "timeStamp": "2020-12-07T07:45:00Z",
      "items": [
        {
          "name": "mobilePercent",
          "value": "49.732169"
        },
        {
          "name": "desktopPercent",
          "value": "50.269819"
        },
        {
          "name": "otherDevicePercent",
          "value": "0.100375"
        }
      ]
    },
    {
      "timeStamp": "2020-12-07T08:00:00Z",
      "items": [
        {
          "name": "mobilePercent",
          "value": "49.767734"
        },
        {
          "name": "desktopPercent",
          "value": "50.239140"
        },
        {
          "name": "otherDevicePercent",
          "value": "0.094281"
        }
      ]
    },
    {
      "timeStamp": "2020-12-07T08:15:00Z",
      "items": [
        {
          "name": "mobilePercent",
          "value": "49.021584"
        },
        {
          "name": "desktopPercent",
          "value": "50.982330"
        },
        {
          "name": "otherDevicePercent",
          "value": "0.087079"
        }
      ]
    },
    {
      "timeStamp": "2020-12-07T08:30:00Z",
      "items": [
        {
          "name": "mobilePercent",
          "value": "48.723041"
        },
        {
          "name": "desktopPercent",
          "value": "51.279865"
        },
        {
          "name": "otherDevicePercent",
          "value": "0.094948"
        }
      ]
    },
    {
      "timeStamp": "2020-12-07T08:45:00Z",
      "items": [
        {
          "name": "mobilePercent",
          "value": "48.563790"
        },
        {
          "name": "desktopPercent",
          "value": "51.438141"
        },
        {
          "name": "otherDevicePercent",
          "value": "0.079146"
        }
      ]
    },
    {
      "timeStamp": "2020-12-07T09:00:00Z",
      "items": [
        {
          "name": "mobilePercent",
          "value": "48.573483"
        },
        {
          "name": "desktopPercent",
          "value": "51.434187"
        },
        {
          "name": "otherDevicePercent",
          "value": "0.082447"
        }
      ]
    },
    {
      "timeStamp": "2020-12-07T09:15:00Z",
      "items": [
        {
          "name": "mobilePercent",
          "value": "48.297040"
        },
        {
          "name": "desktopPercent",
          "value": "51.705817"
        },
        {
          "name": "otherDevicePercent",
          "value": "0.064748"
        }
      ]
    },
    {
      "timeStamp": "2020-12-07T09:30:00Z",
      "items": [
        {
          "name": "mobilePercent",
          "value": "48.020306"
        },
        {
          "name": "desktopPercent",
          "value": "51.981596"
        },
        {
          "name": "otherDevicePercent",
          "value": "0.076051"
        }
      ]
    },
    {
      "timeStamp": "2020-12-07T09:45:00Z",
      "items": [
        {
          "name": "mobilePercent",
          "value": "48.316513"
        },
        {
          "name": "desktopPercent",
          "value": "51.690984"
        },
        {
          "name": "otherDevicePercent",
          "value": "0.074030"
        }
      ]
    },
    {
      "timeStamp": "2020-12-07T10:00:00Z",
      "items": [
        {
          "name": "mobilePercent",
          "value": "48.770431"
        },
        {
          "name": "desktopPercent",
          "value": "51.234212"
        },
        {
          "name": "otherDevicePercent",
          "value": "0.082652"
        }
      ]
    },
    {
      "timeStamp": "2020-12-07T10:15:00Z",
      "items": [
        {
          "name": "mobilePercent",
          "value": "48.840630"
        },
        {
          "name": "desktopPercent",
          "value": "51.163967"
        },
        {
          "name": "otherDevicePercent",
          "value": "0.091940"
        }
      ]
    },
    {
      "timeStamp": "2020-12-07T10:30:00Z",
      "items": [
        {
          "name": "mobilePercent",
          "value": "48.683828"
        },
        {
          "name": "desktopPercent",
          "value": "51.319808"
        },
        {
          "name": "otherDevicePercent",
          "value": "0.106348"
        }
      ]
    },
    {
      "timeStamp": "2020-12-07T10:45:00Z",
      "items": [
        {
          "name": "mobilePercent",
          "value": "48.849311"
        },
        {
          "name": "desktopPercent",
          "value": "51.157929"
        },
        {
          "name": "otherDevicePercent",
          "value": "0.085069"
        }
      ]
    },
    {
      "timeStamp": "2020-12-07T11:00:00Z",
      "items": [
        {
          "name": "mobilePercent",
          "value": "49.245209"
        },
        {
          "name": "desktopPercent",
          "value": "50.761036"
        },
        {
          "name": "otherDevicePercent",
          "value": "0.080297"
        }
      ]
    }
  ]
}