{
  "startTimeStamp": "2020-10-19T18:00:00Z",
  "endTimeStamp": "2020-10-20T00:00:00Z",
  "timeRange": [
    {
      "timeStamp": "2020-10-19T18:00:00Z",
      "items": [
        {
          "name": "netflowChange",
          "value": "1.068607"
        }
      ]
    },
    {
      "timeStamp": "2020-10-19T18:15:00Z",
      "items": [
        {
          "name": "netflowChange",
          "value": "1.096531"
        }
      ]
    },
    {
      "timeStamp": "2020-10-19T18:30:00Z",
      "items": [
        {
          "name": "netflowChange",
          "value": "1.111512"
        }
      ]
    },
    {
      "timeStamp": "2020-10-19T18:45:00Z",
      "items": [
        {
          "name": "netflowChange",
          "value": "1.122133"
        }
      ]
    },
    {
      "timeStamp": "2020-10-19T19:00:00Z",
      "items": [
        {
          "name": "netflowChange",
          "value": "1.127758"
        }
      ]
    },
    {
      "timeStamp": "2020-10-19T19:15:00Z",
      "items": [
        {
          "name": "netflowChange",
          "value": "1.128244"
        }
      ]
    },
    {
      "timeStamp": "2020-10-19T19:30:00Z",
      "items": [
        {
          "name": "netflowChange",
          "value": "1.125373"
        }
      ]
    },
    {
      "timeStamp": "2020-10-19T19:45:00Z",
      "items": [
        {
          "name": "netflowChange",
          "value": "1.120480"
        }
      ]
    },
    {
      "timeStamp": "2020-10-19T20:00:00Z",
      "items": [
        {
          "name": "netflowChange",
          "value": "1.114907"
        }
      ]
    },
    {
      "timeStamp": "2020-10-19T20:15:00Z",
      "items": [
        {
          "name": "netflowChange",
          "value": "1.109750"
        }
      ]
    },
    {
      "timeStamp": "2020-10-19T20:30:00Z",
      "items": [
        {
          "name": "netflowChange",
          "value": "1.102723"
        }
      ]
    },
    {
      "timeStamp": "2020-10-19T20:45:00Z",
      "items": [
        {
          "name": "netflowChange",
          "value": "1.095837"
        }
      ]
    },
    {
      "timeStamp": "2020-10-19T21:00:00Z",
      "items": [
        {
          "name": "netflowChange",
          "value": "1.087955"
        }
      ]
    },
    {
      "timeStamp": "2020-10-19T21:15:00Z",
      "items": [
        {
          "name": "netflowChange",
          "value": "1.080452"
        }
      ]
    },
    {
      "timeStamp": "2020-10-19T21:30:00Z",
      "items": [
        {
          "name": "netflowChange",
          "value": "1.071833"
        }
      ]
    },
    {
      "timeStamp": "2020-10-19T21:45:00Z",
      "items": [
        {
          "name": "netflowChange",
          "value": "1.062280"
        }
      ]
    },
    {
      "timeStamp": "2020-10-19T22:00:00Z",
      "items": [
        {
          "name": "netflowChange",
          "value": "1.055124"
        }
      ]
    },
    {
      "timeStamp": "2020-10-19T22:15:00Z",
      "items": [
        {
          "name": "netflowChange",
          "value": "1.046222"
        }
      ]
    },
    {
      "timeStamp": "2020-10-19T22:30:00Z",
      "items": [
        {
          "name": "netflowChange",
          "value": "1.036861"
        }
      ]
    },
    {
      "timeStamp": "2020-10-19T22:45:00Z",
      "items": [
        {
          "name": "netflowChange",
          "value": "1.028571"
        }
      ]
    },
    {
      "timeStamp": "2020-10-19T23:00:00Z",
      "items": [
        {
          "name": "netflowChange",
          "value": "1.021632"
        }
      ]
    },
    {
      "timeStamp": "2020-10-19T23:15:00Z",
      "items": [
        {
          "name": "netflowChange",
          "value": "1.014023"
        }
      ]
    },
    {
      "timeStamp": "2020-10-19T23:30:00Z",
      "items": [
        {
          "name": "netflowChange",
          "value": "1.006240"
        }
      ]
    },
    {
      "timeStamp": "2020-10-19T23:45:00Z",
      "items": [
        {
          "name": "netflowChange",
          "value": "0.997306"
        }
      ]
    }
  ]
}